plex_updater/__init__.py
plex_updater/__main__.py
plex_updater/plex_updater.py
plex_updater-0.1.0.dist-info/METADATA
plex_updater-0.1.0.dist-info/WHEEL
plex_updater-0.1.0.dist-info/entry_points.txt
plex_updater-0.1.0.dist-info/top_level.txt
plex_updater-0.1.0.dist-info/RECORD
