Metadata-Version: 2.1
Name: plex-updater
Version: 0.1.0
Summary: UNKNOWN
Home-page: UNKNOWN
License: UNKNOWN
Platform: UNKNOWN
Requires-Dist: requests
Requires-Dist: python-apt
Requires-Dist: importlib ; python_version == "2.6"
